s3inspect/__init__.py
s3inspect/__main__.py
s3inspect/s3inspect.py
S3_Inspect-1.4.dist-info/LICENSE
S3_Inspect-1.4.dist-info/METADATA
S3_Inspect-1.4.dist-info/WHEEL
S3_Inspect-1.4.dist-info/top_level.txt
S3_Inspect-1.4.dist-info/RECORD
