Metadata-Version: 2.1
Name: S3-Inspect
Version: 1.4
Summary: A package to inspect contents of S3 buckets and generate report
Home-page: https://github.com/syedhumair/aws-devops-challenge
Author: Syed Humair
Author-email: syed.humair@gmail.com
License: Creative Commons Attribution-Noncommercial-Share Alike license
Keywords: aws,s3,challenge
Platform: UNKNOWN
Requires-Dist: boto3 (==1.9.151)
Requires-Dist: botocore (==1.12.151)
Requires-Dist: docutils (==0.14)
Requires-Dist: jmespath (==0.9.4)
Requires-Dist: python-dateutil (==2.8.0)
Requires-Dist: s3transfer (==0.2.0)
Requires-Dist: six (==1.12.0)
Requires-Dist: urllib3 (==1.24.3)
